{
  "attributes": {
    "sys:administrativeLevel": 4,
    "sys:locationType": "ward",
    "sys:parentLocation": "entity:location/municipality/madhya-bindu-municipality"
  },
  "attributions": [
    "https://github.com/sagautam5/local-states-nepal"
  ],
  "contacts": null,
  "createdAt": "2025-11-04 20:57:13.357839",
  "description": null,
  "id": "entity:location/ward/madhya-bindu-municipality---ward-5",
  "identifiers": null,
  "misspelledNames": null,
  "names": [
    {
      "kind": "DEFAULT",
      "lang": "en",
      "value": "Madhya Bindu Municipality - Ward 5"
    },
    {
      "kind": "DEFAULT",
      "lang": "ne",
      "value": "मध्यविन्दु नगरपालिका वडा नं.– 5"
    }
  ],
  "short_description": null,
  "slug": "madhya-bindu-municipality---ward-5",
  "subType": "ward",
  "tags": null,
  "type": "location",
  "versionSummary": {
    "actor": {
      "id": "actor:location-np-importer",
      "name": "Location NP Importer",
      "slug": "location-np-importer"
    },
    "changeDescription": "Imported from Nepal administrative map data",
    "createdAt": "2025-11-04 20:57:13.357839",
    "entityOrRelationshipId": "entity:location/ward/madhya-bindu-municipality---ward-5",
    "id": "version:entity:location/ward/madhya-bindu-municipality---ward-5:1",
    "type": "ENTITY",
    "versionNumber": 1
  }
}