{
  "actor": {
    "id": "actor:csv-importer",
    "name": "CSV Data Importer",
    "slug": "csv-importer"
  },
  "changeDescription": "Initial creation from CSV data",
  "changes": {},
  "createdAt": "2025-11-03 21:55:41.398493",
  "entityOrRelationshipId": "entity:organization/government-body/machapuchre-bank-ltd",
  "id": "version:entity:organization/government-body/machapuchre-bank-ltd:1",
  "snapshot": {
    "attributes": {
      "address": "Lazimpat",
      "sys:governmentType": "unknown",
      "sys:location:district": "Kathmandu"
    },
    "attributions": [
      "OpenKnowledge Nepal"
    ],
    "contacts": [
      {
        "label": null,
        "type": "email",
        "value": "machbank@mbl.com.np"
      },
      {
        "label": null,
        "type": "phone",
        "value": "01-5970555"
      },
      {
        "label": null,
        "type": "website",
        "value": "https://www.machbank.com/"
      }
    ],
    "createdAt": "2025-11-03 21:55:41.398493",
    "description": null,
    "id": "entity:organization/government_body/machapuchre-bank-ltd",
    "identifiers": null,
    "misspelledNames": null,
    "names": [
      {
        "kind": "DEFAULT",
        "lang": "en",
        "value": "Machapuchre Bank Ltd"
      }
    ],
    "short_description": "Government body in Kathmandu",
    "slug": "machapuchre-bank-ltd",
    "subType": "government_body",
    "tags": null,
    "type": "organization",
    "versionSummary": {
      "actor": {
        "id": "actor:csv-importer",
        "name": "CSV Data Importer",
        "slug": "csv-importer"
      },
      "changeDescription": "Initial creation from CSV data",
      "createdAt": "2025-11-03 21:55:41.398493",
      "entityOrRelationshipId": "entity:organization/government-body/machapuchre-bank-ltd",
      "id": "version:entity:organization/government-body/machapuchre-bank-ltd:1",
      "type": "ENTITY",
      "versionNumber": 1
    }
  },
  "type": "ENTITY",
  "versionNumber": 1
}