{
  "actor": {
    "id": "actor:location-np-importer",
    "name": "Location NP Importer",
    "slug": "location-np-importer"
  },
  "changeDescription": "Imported from Nepal administrative map data",
  "changes": {},
  "createdAt": "2025-11-04 20:57:13.499492",
  "entityOrRelationshipId": "entity:location/municipality/ramgram-municipality",
  "id": "version:entity:location/municipality/ramgram-municipality:1",
  "snapshot": {
    "attributes": {
      "sys:administrativeLevel": 3,
      "sys:area": 128.32,
      "sys:locationType": "municipality",
      "sys:parentLocation": "entity:location/district/parasi"
    },
    "attributions": [
      "https://github.com/sagautam5/local-states-nepal"
    ],
    "contacts": null,
    "createdAt": "2025-11-04 20:57:13.499492",
    "description": null,
    "id": "entity:location/municipality/ramgram-municipality",
    "identifiers": {
      "website": "http://www.ramgrammun.gov.np/"
    },
    "misspelledNames": null,
    "names": [
      {
        "kind": "DEFAULT",
        "lang": "en",
        "value": "Ramgram Municipality"
      },
      {
        "kind": "DEFAULT",
        "lang": "ne",
        "value": "रामग्राम नगरपालिका"
      }
    ],
    "short_description": null,
    "slug": "ramgram-municipality",
    "subType": "municipality",
    "tags": null,
    "type": "location",
    "versionSummary": {
      "actor": {
        "id": "actor:location-np-importer",
        "name": "Location NP Importer",
        "slug": "location-np-importer"
      },
      "changeDescription": "Imported from Nepal administrative map data",
      "createdAt": "2025-11-04 20:57:13.499492",
      "entityOrRelationshipId": "entity:location/municipality/ramgram-municipality",
      "id": "version:entity:location/municipality/ramgram-municipality:1",
      "type": "ENTITY",
      "versionNumber": 1
    }
  },
  "type": "ENTITY",
  "versionNumber": 1
}