{
  "attributes": {
    "sys:administrativeLevel": 3,
    "sys:area": 157.4,
    "sys:locationType": "municipality",
    "sys:parentLocation": "entity:location/district/bara"
  },
  "attributions": [
    "https://github.com/sagautam5/local-states-nepal"
  ],
  "contacts": null,
  "createdAt": "2025-11-04 20:57:12.316915",
  "description": null,
  "id": "entity:location/municipality/kolhabi-municipality",
  "identifiers": {
    "website": "http://www.kolhabimun.gov.np/"
  },
  "misspelledNames": null,
  "names": [
    {
      "kind": "DEFAULT",
      "lang": "en",
      "value": "Kolhabi Municipality"
    },
    {
      "kind": "DEFAULT",
      "lang": "ne",
      "value": "कोल्हवी नगरपालिका"
    }
  ],
  "short_description": null,
  "slug": "kolhabi-municipality",
  "subType": "municipality",
  "tags": null,
  "type": "location",
  "versionSummary": {
    "actor": {
      "id": "actor:location-np-importer",
      "name": "Location NP Importer",
      "slug": "location-np-importer"
    },
    "changeDescription": "Imported from Nepal administrative map data",
    "createdAt": "2025-11-04 20:57:12.316915",
    "entityOrRelationshipId": "entity:location/municipality/kolhabi-municipality",
    "id": "version:entity:location/municipality/kolhabi-municipality:1",
    "type": "ENTITY",
    "versionNumber": 1
  }
}