{
  "attributes": {
    "nationality": "Nepali",
    "political_party": "Nepali Congress",
    "sys:positions": [
      {
        "organization": "Nepali Congress",
        "startDate": "1999-01-01T00:00:00",
        "title": "Member of the Pratinidhi Sabha"
      },
      {
        "title": "Minister of Industry, Commerce and Supplies"
      },
      {
        "title": "Minister of Health"
      },
      {
        "organization": "Nepali Congress",
        "title": "Treasurer"
      }
    ]
  },
  "attributions": [
    "Wikipedia"
  ],
  "contacts": null,
  "createdAt": "2025-11-02 12:05:04.109931",
  "description": "Ram Krishna Tamrakar is a Nepalese politician representing the Nepali Congress party. He was elected to the Pratinidhi Sabha in the 1999 election. Following his election, he was appointed Minister of Industry, Commerce and Supplies, and later served as the Minister of Health. Tamrakar is the Treasurer of the Nepali Congress. In 2005, he was arrested in connection with anti-royal protests.",
  "id": "entity:person/ram-krishna-tamrakar",
  "identifiers": {
    "wikipedia_en": "https://en.wikipedia.org/wiki/Ram_Krishna_Tamrakar"
  },
  "misspelledNames": null,
  "names": [
    {
      "kind": "DEFAULT",
      "lang": "en",
      "value": "Ram Krishna Tamrakar"
    }
  ],
  "short_description": "Nepali politician who has served as Minister of Industry, Commerce and Supplies, and Minister of Health.",
  "slug": "ram-krishna-tamrakar",
  "subType": null,
  "tags": [
    "Politician",
    "Nepali Congress"
  ],
  "type": "person",
  "versionSummary": {
    "actor": {
      "id": "actor:system",
      "name": "System user",
      "slug": "system"
    },
    "changeDescription": "Initial version",
    "createdAt": "2025-11-02 12:05:04.109931",
    "entityOrRelationshipId": "entity:person/ram-krishna-tamrakar",
    "id": "version:entity:person/ram-krishna-tamrakar:1",
    "type": "ENTITY",
    "versionNumber": 1
  }
}