{
  "attributes": {
    "nationality": "Nepali",
    "political_party": "Communist Party of Nepal (Maoist Centre)",
    "sys:positions": [
      {
        "organization": "Constituent Assembly of Nepal",
        "startDate": "2008-01-01T00:00:00",
        "title": "Member of the Constituent Assembly"
      }
    ]
  },
  "attributions": [
    "Wikipedia"
  ],
  "contacts": null,
  "createdAt": "2025-11-02 09:51:55.901644",
  "description": "Rupa So.Si. Chaudhari is a Nepalese politician, belonging to the Communist Party of Nepal (Maoist Centre). In the 2008 Constituent Assembly election she was elected from the Kailali-1 constituency, winning 21780 votes.",
  "id": "entity:person/rupa-sosi-chaudhari",
  "identifiers": {
    "wikipedia_en": "https://en.wikipedia.org/wiki/Rupa_So.Si._Chaudhari"
  },
  "misspelledNames": null,
  "names": [
    {
      "kind": "DEFAULT",
      "lang": "en",
      "value": "Rupa So.Si. Chaudhari"
    },
    {
      "kind": "DEFAULT",
      "lang": "ne",
      "value": "रुपा सोसी चौधरी"
    }
  ],
  "short_description": "Nepali politician",
  "slug": "rupa-sosi-chaudhari",
  "subType": null,
  "tags": [
    "politician"
  ],
  "type": "person",
  "versionSummary": {
    "actor": {
      "id": "actor:system",
      "name": "System user",
      "slug": "system"
    },
    "changeDescription": "Initial version",
    "createdAt": "2025-11-02 09:51:55.901644",
    "entityOrRelationshipId": "entity:person/rupa-sosi-chaudhari",
    "id": "version:entity:person/rupa-sosi-chaudhari:1",
    "type": "ENTITY",
    "versionNumber": 1
  }
}