{
  "attributes": {
    "known_as": "Ambedkar of Nepal",
    "nationality": "Nepali",
    "religion": "Buddhism",
    "sys:education": [
      {
        "institution": "Tribhuvan University"
      }
    ],
    "sys:positions": [
      {
        "organization": "Government of Nepal",
        "title": "Minister of Science, Technology, Environment and Population"
      },
      {
        "organization": "Bahujan Shakti Party",
        "title": "President"
      },
      {
        "organization": "Dalit Janajati Party",
        "title": "Chairman"
      },
      {
        "organization": "Dalit Janajati Party",
        "title": "Member of the Nepalese Constituent Assembly"
      }
    ]
  },
  "attributions": [
    "Wikipedia"
  ],
  "contacts": null,
  "createdAt": "2025-11-02 11:20:44.539351",
  "description": "Vishwendra Paswan is a Nepalese politician and human rights activist from the Dalit community who follows Buddhism. He is the president of the Bahujan Shakti Party and was the chairman of the Dalit Janajati Party. He served as a member of the Nepalese Constituent Assembly after the 2008 election and as Minister of Science, Technology, Environment and Population for the Government of Nepal. An avowed Ambedkarite, he is known as the \"Ambedkar of Nepal\".",
  "id": "entity:person/vishwendra-paswan",
  "identifiers": {
    "wikipedia_en": "https://en.wikipedia.org/wiki/Biswendra_Paswan"
  },
  "misspelledNames": [
    {
      "kind": "DEFAULT",
      "lang": "en",
      "value": "Biswendra Paswan"
    },
    {
      "kind": "DEFAULT",
      "lang": "en",
      "value": "Vishwendraman Pashwan"
    }
  ],
  "names": [
    {
      "kind": "DEFAULT",
      "lang": "en",
      "value": "Vishwendra Paswan"
    },
    {
      "kind": "DEFAULT",
      "lang": "ne",
      "value": "विश्वेन्द्र पासवान"
    }
  ],
  "short_description": "Nepalese politician, human rights activist, and former government minister from the Dalit community.",
  "slug": "vishwendra-paswan",
  "subType": null,
  "tags": [
    "politician",
    "human rights activist",
    "Ambedkarite",
    "Dalit"
  ],
  "type": "person",
  "versionSummary": {
    "actor": {
      "id": "actor:system",
      "name": "System user",
      "slug": "system"
    },
    "changeDescription": "Initial version",
    "createdAt": "2025-11-02 11:20:44.539351",
    "entityOrRelationshipId": "entity:person/vishwendra-paswan",
    "id": "version:entity:person/vishwendra-paswan:1",
    "type": "ENTITY",
    "versionNumber": 1
  }
}