{
  "actor": {
    "id": "actor:location-np-importer",
    "name": "Location NP Importer",
    "slug": "location-np-importer"
  },
  "changeDescription": "Imported from Nepal administrative map data",
  "changes": {},
  "createdAt": "2025-11-04 20:57:13.493970",
  "entityOrRelationshipId": "entity:location/district/parasi",
  "id": "version:entity:location/district/parasi:1",
  "snapshot": {
    "attributes": {
      "sys:administrativeLevel": 2,
      "sys:area": 634.88,
      "sys:headquarter_en": "Ramgram",
      "sys:headquarter_ne": "रामग्राम",
      "sys:locationType": "district",
      "sys:parentLocation": "entity:location/province/lumbini"
    },
    "attributions": [
      "https://github.com/sagautam5/local-states-nepal"
    ],
    "contacts": null,
    "createdAt": "2025-11-04 20:57:13.493970",
    "description": null,
    "id": "entity:location/district/parasi",
    "identifiers": {
      "website": "https://dccnawalparasi.gov.np/"
    },
    "misspelledNames": null,
    "names": [
      {
        "kind": "DEFAULT",
        "lang": "en",
        "value": "Parasi"
      },
      {
        "kind": "DEFAULT",
        "lang": "ne",
        "value": "परासी"
      }
    ],
    "short_description": null,
    "slug": "parasi",
    "subType": "district",
    "tags": null,
    "type": "location",
    "versionSummary": {
      "actor": {
        "id": "actor:location-np-importer",
        "name": "Location NP Importer",
        "slug": "location-np-importer"
      },
      "changeDescription": "Imported from Nepal administrative map data",
      "createdAt": "2025-11-04 20:57:13.493970",
      "entityOrRelationshipId": "entity:location/district/parasi",
      "id": "version:entity:location/district/parasi:1",
      "type": "ENTITY",
      "versionNumber": 1
    }
  },
  "type": "ENTITY",
  "versionNumber": 1
}